[
  {
    "status": "success"
  },
  {
    "username": "dependabot[bot]",
    "totalPRs": 53,
    "mergedPRs": 19,
    "totalIssues": 0
  },
  {
    "username": "perazz",
    "totalPRs": 17,
    "mergedPRs": 17,
    "totalIssues": 0
  },
  {
    "username": "srinjoy933",
    "totalPRs": 21,
    "mergedPRs": 10,
    "totalIssues": 17
  },
  {
    "username": "jvdp1",
    "totalPRs": 11,
    "mergedPRs": 10,
    "totalIssues": 0
  },
  {
    "username": "wpbonelli",
    "totalPRs": 10,
    "mergedPRs": 10,
    "totalIssues": 0
  },
  {
    "username": "gnikit",
    "totalPRs": 10,
    "mergedPRs": 8,
    "totalIssues": 0
  },
  {
    "username": "jalvesz",
    "totalPRs": 9,
    "mergedPRs": 6,
    "totalIssues": 4
  },
  {
    "username": "joewallwork",
    "totalPRs": 7,
    "mergedPRs": 6,
    "totalIssues": 11
  },
  {
    "username": "Mahmood-Sinan",
    "totalPRs": 7,
    "mergedPRs": 6,
    "totalIssues": 2
  },
  {
    "username": "github-actions[bot]",
    "totalPRs": 17,
    "mergedPRs": 5,
    "totalIssues": 0
  },
  {
    "username": "JAi-SATHVIK",
    "totalPRs": 10,
    "mergedPRs": 5,
    "totalIssues": 3
  },
  {
    "username": "ZainabTravadi",
    "totalPRs": 9,
    "mergedPRs": 3,
    "totalIssues": 8
  },
  {
    "username": "ijatinydv",
    "totalPRs": 8,
    "mergedPRs": 3,
    "totalIssues": 2
  },
  {
    "username": "fengfeng-zi",
    "totalPRs": 7,
    "mergedPRs": 3,
    "totalIssues": 0
  },
  {
    "username": "loiseaujc",
    "totalPRs": 5,
    "mergedPRs": 3,
    "totalIssues": 0
  },
  {
    "username": "fiolj",
    "totalPRs": 5,
    "mergedPRs": 3,
    "totalIssues": 2
  },
  {
    "username": "zandivx",
    "totalPRs": 6,
    "mergedPRs": 2,
    "totalIssues": 1
  },
  {
    "username": "aamrindersingh",
    "totalPRs": 4,
    "mergedPRs": 2,
    "totalIssues": 0
  },
  {
    "username": "awvwgk",
    "totalPRs": 4,
    "mergedPRs": 2,
    "totalIssues": 1
  },
  {
    "username": "stigh",
    "totalPRs": 3,
    "mergedPRs": 2,
    "totalIssues": 0
  },
  {
    "username": "Calluumm",
    "totalPRs": 3,
    "mergedPRs": 2,
    "totalIssues": 0
  },
  {
    "username": "lukaswittmann",
    "totalPRs": 2,
    "mergedPRs": 2,
    "totalIssues": 3
  },
  {
    "username": "JorgeG94",
    "totalPRs": 2,
    "mergedPRs": 2,
    "totalIssues": 1
  },
  {
    "username": "krystophny",
    "totalPRs": 14,
    "mergedPRs": 1,
    "totalIssues": 1
  },
  {
    "username": "DharunMR",
    "totalPRs": 5,
    "mergedPRs": 1,
    "totalIssues": 0
  },
  {
    "username": "Ayushishivhare09",
    "totalPRs": 4,
    "mergedPRs": 1,
    "totalIssues": 0
  },
  {
    "username": "alanocallaghan",
    "totalPRs": 3,
    "mergedPRs": 1,
    "totalIssues": 0
  },
  {
    "username": "pre-commit-ci[bot]",
    "totalPRs": 2,
    "mergedPRs": 1,
    "totalIssues": 0
  },
  {
    "username": "amckinstry",
    "totalPRs": 2,
    "mergedPRs": 1,
    "totalIssues": 2
  },
  {
    "username": "pseewald",
    "totalPRs": 2,
    "mergedPRs": 1,
    "totalIssues": 2
  },
  {
    "username": "zbeekman",
    "totalPRs": 1,
    "mergedPRs": 1,
    "totalIssues": 3
  },
  {
    "username": "gha3mi",
    "totalPRs": 1,
    "mergedPRs": 1,
    "totalIssues": 2
  },
  {
    "username": "zoziha",
    "totalPRs": 1,
    "mergedPRs": 1,
    "totalIssues": 2
  },
  {
    "username": "grisuthedragon",
    "totalPRs": 1,
    "mergedPRs": 1,
    "totalIssues": 1
  },
  {
    "username": "jinangshah21",
    "totalPRs": 1,
    "mergedPRs": 1,
    "totalIssues": 0
  },
  {
    "username": "danieljprice",
    "totalPRs": 1,
    "mergedPRs": 1,
    "totalIssues": 1
  },
  {
    "username": "MadhurKumar004",
    "totalPRs": 1,
    "mergedPRs": 1,
    "totalIssues": 0
  },
  {
    "username": "Copilot",
    "totalPRs": 1,
    "mergedPRs": 1,
    "totalIssues": 0
  },
  {
    "username": "BaumiCoder",
    "totalPRs": 1,
    "mergedPRs": 1,
    "totalIssues": 0
  },
  {
    "username": "N00byKing",
    "totalPRs": 1,
    "mergedPRs": 1,
    "totalIssues": 0
  },
  {
    "username": "ghost",
    "totalPRs": 8,
    "mergedPRs": 0,
    "totalIssues": 0
  },
  {
    "username": "dhruvch12",
    "totalPRs": 2,
    "mergedPRs": 0,
    "totalIssues": 0
  },
  {
    "username": "Adityazzzzz",
    "totalPRs": 2,
    "mergedPRs": 0,
    "totalIssues": 0
  },
  {
    "username": "utsav-pal",
    "totalPRs": 2,
    "mergedPRs": 0,
    "totalIssues": 0
  },
  {
    "username": "MooSayed1",
    "totalPRs": 2,
    "mergedPRs": 0,
    "totalIssues": 0
  },
  {
    "username": "sajjanmanoj26-code",
    "totalPRs": 1,
    "mergedPRs": 0,
    "totalIssues": 0
  },
  {
    "username": "JeffIrwin",
    "totalPRs": 1,
    "mergedPRs": 0,
    "totalIssues": 1
  },
  {
    "username": "ANAS727189",
    "totalPRs": 1,
    "mergedPRs": 0,
    "totalIssues": 0
  },
  {
    "username": "td-mpcdf",
    "totalPRs": 1,
    "mergedPRs": 0,
    "totalIssues": 0
  },
  {
    "username": "max-models",
    "totalPRs": 1,
    "mergedPRs": 0,
    "totalIssues": 0
  },
  {
    "username": "dbroemmel",
    "totalPRs": 1,
    "mergedPRs": 0,
    "totalIssues": 0
  },
  {
    "username": "14NGiestas",
    "totalPRs": 1,
    "mergedPRs": 0,
    "totalIssues": 0
  },
  {
    "username": "RatanKokal",
    "totalPRs": 1,
    "mergedPRs": 0,
    "totalIssues": 0
  },
  {
    "username": "edish-github",
    "totalPRs": 1,
    "mergedPRs": 0,
    "totalIssues": 0
  },
  {
    "username": "learner0018",
    "totalPRs": 1,
    "mergedPRs": 0,
    "totalIssues": 0
  },
  {
    "username": "mvanhorn",
    "totalPRs": 1,
    "mergedPRs": 0,
    "totalIssues": 0
  },
  {
    "username": "sbryngelson",
    "totalPRs": 1,
    "mergedPRs": 0,
    "totalIssues": 0
  },
  {
    "username": "sahilkhedkar",
    "totalPRs": 1,
    "mergedPRs": 0,
    "totalIssues": 0
  },
  {
    "username": "LiamPattinson",
    "totalPRs": 1,
    "mergedPRs": 0,
    "totalIssues": 0
  },
  {
    "username": "agsaru",
    "totalPRs": 1,
    "mergedPRs": 0,
    "totalIssues": 0
  },
  {
    "username": "aviralnull",
    "totalPRs": 1,
    "mergedPRs": 0,
    "totalIssues": 0
  },
  {
    "username": "MuellerSeb",
    "totalPRs": 1,
    "mergedPRs": 0,
    "totalIssues": 1
  },
  {
    "username": "arjenmarkusdeltaresnl",
    "totalPRs": 0,
    "mergedPRs": 0,
    "totalIssues": 1
  },
  {
    "username": "diegojco",
    "totalPRs": 0,
    "mergedPRs": 0,
    "totalIssues": 1
  },
  {
    "username": "poopPOT101",
    "totalPRs": 0,
    "mergedPRs": 0,
    "totalIssues": 1
  },
  {
    "username": "rljacob",
    "totalPRs": 0,
    "mergedPRs": 0,
    "totalIssues": 1
  },
  {
    "username": "bonachea",
    "totalPRs": 0,
    "mergedPRs": 0,
    "totalIssues": 3
  },
  {
    "username": "DrK",
    "totalPRs": 0,
    "mergedPRs": 0,
    "totalIssues": 1
  },
  {
    "username": "LaplaceSoda",
    "totalPRs": 0,
    "mergedPRs": 0,
    "totalIssues": 1
  },
  {
    "username": "minhqdao",
    "totalPRs": 0,
    "mergedPRs": 0,
    "totalIssues": 1
  },
  {
    "username": "certik",
    "totalPRs": 0,
    "mergedPRs": 0,
    "totalIssues": 2
  },
  {
    "username": "mind-bending-forks",
    "totalPRs": 0,
    "mergedPRs": 0,
    "totalIssues": 2
  },
  {
    "username": "qwerdenkerXD",
    "totalPRs": 0,
    "mergedPRs": 0,
    "totalIssues": 1
  },
  {
    "username": "StackPancakes",
    "totalPRs": 0,
    "mergedPRs": 0,
    "totalIssues": 1
  },
  {
    "username": "Carltoffel",
    "totalPRs": 0,
    "mergedPRs": 0,
    "totalIssues": 1
  },
  {
    "username": "davidpfister",
    "totalPRs": 0,
    "mergedPRs": 0,
    "totalIssues": 2
  },
  {
    "username": "AdamZettel",
    "totalPRs": 0,
    "mergedPRs": 0,
    "totalIssues": 1
  },
  {
    "username": "lqz-hub",
    "totalPRs": 0,
    "mergedPRs": 0,
    "totalIssues": 1
  },
  {
    "username": "pchakraborty",
    "totalPRs": 0,
    "mergedPRs": 0,
    "totalIssues": 1
  },
  {
    "username": "sebastian-mutz",
    "totalPRs": 0,
    "mergedPRs": 0,
    "totalIssues": 4
  },
  {
    "username": "aamaricci",
    "totalPRs": 0,
    "mergedPRs": 0,
    "totalIssues": 1
  },
  {
    "username": "zaikunzhang",
    "totalPRs": 0,
    "mergedPRs": 0,
    "totalIssues": 5
  },
  {
    "username": "sshestov",
    "totalPRs": 0,
    "mergedPRs": 0,
    "totalIssues": 1
  },
  {
    "username": "AlexanderGSC",
    "totalPRs": 0,
    "mergedPRs": 0,
    "totalIssues": 1
  },
  {
    "username": "SteamPower101",
    "totalPRs": 0,
    "mergedPRs": 0,
    "totalIssues": 3
  },
  {
    "username": "JASory",
    "totalPRs": 0,
    "mergedPRs": 0,
    "totalIssues": 1
  },
  {
    "username": "ssoehdata",
    "totalPRs": 0,
    "mergedPRs": 0,
    "totalIssues": 1
  },
  {
    "username": "rouson",
    "totalPRs": 0,
    "mergedPRs": 0,
    "totalIssues": 1
  },
  {
    "username": "chhavx1618",
    "totalPRs": 0,
    "mergedPRs": 0,
    "totalIssues": 1
  },
  {
    "username": "TiborGY",
    "totalPRs": 0,
    "mergedPRs": 0,
    "totalIssues": 1
  },
  {
    "username": "cradesto",
    "totalPRs": 0,
    "mergedPRs": 0,
    "totalIssues": 1
  },
  {
    "username": "thalesfmac",
    "totalPRs": 0,
    "mergedPRs": 0,
    "totalIssues": 1
  },
  {
    "username": "GuillaumeGrimardKUL",
    "totalPRs": 0,
    "mergedPRs": 0,
    "totalIssues": 1
  },
  {
    "username": "juanmor40",
    "totalPRs": 0,
    "mergedPRs": 0,
    "totalIssues": 1
  }
]