[
  {
    "status": "success"
  },
  {
    "username": "laymonage",
    "totalPRs": 64,
    "mergedPRs": 45,
    "totalIssues": 1
  },
  {
    "username": "thibaudcolas",
    "totalPRs": 33,
    "mergedPRs": 27,
    "totalIssues": 177
  },
  {
    "username": "dependabot[bot]",
    "totalPRs": 31,
    "mergedPRs": 24,
    "totalIssues": 0
  },
  {
    "username": "gasman",
    "totalPRs": 21,
    "mergedPRs": 12,
    "totalIssues": 2
  },
  {
    "username": "vossisboss",
    "totalPRs": 13,
    "mergedPRs": 10,
    "totalIssues": 1
  },
  {
    "username": "Srishti-j18",
    "totalPRs": 12,
    "mergedPRs": 8,
    "totalIssues": 1
  },
  {
    "username": "Raghaddahi",
    "totalPRs": 20,
    "mergedPRs": 7,
    "totalIssues": 0
  },
  {
    "username": "thi-bot",
    "totalPRs": 8,
    "mergedPRs": 6,
    "totalIssues": 0
  },
  {
    "username": "Manny2706",
    "totalPRs": 12,
    "mergedPRs": 5,
    "totalIssues": 0
  },
  {
    "username": "Stormheg",
    "totalPRs": 9,
    "mergedPRs": 5,
    "totalIssues": 0
  },
  {
    "username": "AviraL0013",
    "totalPRs": 9,
    "mergedPRs": 5,
    "totalIssues": 1
  },
  {
    "username": "OluwagbeminiyiA",
    "totalPRs": 8,
    "mergedPRs": 5,
    "totalIssues": 1
  },
  {
    "username": "zerolab",
    "totalPRs": 7,
    "mergedPRs": 5,
    "totalIssues": 9
  },
  {
    "username": "Pra26nav",
    "totalPRs": 9,
    "mergedPRs": 4,
    "totalIssues": 5
  },
  {
    "username": "Marvinrose",
    "totalPRs": 8,
    "mergedPRs": 4,
    "totalIssues": 1
  },
  {
    "username": "RealOrangeOne",
    "totalPRs": 7,
    "mergedPRs": 4,
    "totalIssues": 3
  },
  {
    "username": "shivanginigupta573-dev",
    "totalPRs": 6,
    "mergedPRs": 4,
    "totalIssues": 3
  },
  {
    "username": "lourduradjou",
    "totalPRs": 6,
    "mergedPRs": 4,
    "totalIssues": 0
  },
  {
    "username": "10billionpercent",
    "totalPRs": 5,
    "mergedPRs": 4,
    "totalIssues": 0
  },
  {
    "username": "sushanthaaa",
    "totalPRs": 5,
    "mergedPRs": 4,
    "totalIssues": 0
  },
  {
    "username": "Juwonthefirst",
    "totalPRs": 4,
    "mergedPRs": 4,
    "totalIssues": 1
  },
  {
    "username": "ankit02327",
    "totalPRs": 16,
    "mergedPRs": 3,
    "totalIssues": 0
  },
  {
    "username": "Mustansir-06",
    "totalPRs": 11,
    "mergedPRs": 3,
    "totalIssues": 0
  },
  {
    "username": "dolliecoder",
    "totalPRs": 9,
    "mergedPRs": 3,
    "totalIssues": 0
  },
  {
    "username": "vanshaj2023",
    "totalPRs": 9,
    "mergedPRs": 3,
    "totalIssues": 6
  },
  {
    "username": "Kkt04",
    "totalPRs": 8,
    "mergedPRs": 3,
    "totalIssues": 7
  },
  {
    "username": "AdityaSharma-Git3207",
    "totalPRs": 7,
    "mergedPRs": 3,
    "totalIssues": 6
  },
  {
    "username": "Sneha-Goswami123",
    "totalPRs": 6,
    "mergedPRs": 3,
    "totalIssues": 5
  },
  {
    "username": "Anayo-Anyafulu",
    "totalPRs": 6,
    "mergedPRs": 3,
    "totalIssues": 0
  },
  {
    "username": "srinithivijayakumars139-wq",
    "totalPRs": 6,
    "mergedPRs": 3,
    "totalIssues": 2
  },
  {
    "username": "zanzo2003",
    "totalPRs": 6,
    "mergedPRs": 3,
    "totalIssues": 0
  },
  {
    "username": "NIRMAL20062",
    "totalPRs": 4,
    "mergedPRs": 3,
    "totalIssues": 0
  },
  {
    "username": "DaisyZhang77",
    "totalPRs": 4,
    "mergedPRs": 3,
    "totalIssues": 1
  },
  {
    "username": "aryanyk",
    "totalPRs": 4,
    "mergedPRs": 3,
    "totalIssues": 1
  },
  {
    "username": "kamalakiruthi8",
    "totalPRs": 3,
    "mergedPRs": 3,
    "totalIssues": 1
  },
  {
    "username": "Phinart98",
    "totalPRs": 3,
    "mergedPRs": 3,
    "totalIssues": 0
  },
  {
    "username": "vicky150612",
    "totalPRs": 3,
    "mergedPRs": 3,
    "totalIssues": 0
  },
  {
    "username": "p-r-a-v-i-n",
    "totalPRs": 3,
    "mergedPRs": 3,
    "totalIssues": 0
  },
  {
    "username": "aniketsingh1023",
    "totalPRs": 10,
    "mergedPRs": 2,
    "totalIssues": 0
  },
  {
    "username": "Coder-Ankit001",
    "totalPRs": 8,
    "mergedPRs": 2,
    "totalIssues": 0
  },
  {
    "username": "Adi-gitX",
    "totalPRs": 5,
    "mergedPRs": 2,
    "totalIssues": 0
  },
  {
    "username": "masterking008",
    "totalPRs": 4,
    "mergedPRs": 2,
    "totalIssues": 0
  },
  {
    "username": "nickmoreton",
    "totalPRs": 4,
    "mergedPRs": 2,
    "totalIssues": 0
  },
  {
    "username": "madhvirathor14",
    "totalPRs": 3,
    "mergedPRs": 2,
    "totalIssues": 0
  },
  {
    "username": "CliffordWilsonK",
    "totalPRs": 3,
    "mergedPRs": 2,
    "totalIssues": 0
  },
  {
    "username": "Abiola-Malik",
    "totalPRs": 3,
    "mergedPRs": 2,
    "totalIssues": 0
  },
  {
    "username": "AishwaryaN483",
    "totalPRs": 3,
    "mergedPRs": 2,
    "totalIssues": 2
  },
  {
    "username": "Vaishhnavi27Hub",
    "totalPRs": 3,
    "mergedPRs": 2,
    "totalIssues": 0
  },
  {
    "username": "Nightwing-77",
    "totalPRs": 3,
    "mergedPRs": 2,
    "totalIssues": 0
  },
  {
    "username": "Kaileshwar16",
    "totalPRs": 3,
    "mergedPRs": 2,
    "totalIssues": 0
  },
  {
    "username": "Coll76",
    "totalPRs": 2,
    "mergedPRs": 2,
    "totalIssues": 0
  },
  {
    "username": "SOMASEKAR17",
    "totalPRs": 2,
    "mergedPRs": 2,
    "totalIssues": 1
  },
  {
    "username": "JoelVelasqueZz",
    "totalPRs": 2,
    "mergedPRs": 2,
    "totalIssues": 0
  },
  {
    "username": "LunaaaaZzz",
    "totalPRs": 2,
    "mergedPRs": 2,
    "totalIssues": 0
  },
  {
    "username": "mikko2577",
    "totalPRs": 2,
    "mergedPRs": 2,
    "totalIssues": 0
  },
  {
    "username": "tbrlpld",
    "totalPRs": 2,
    "mergedPRs": 2,
    "totalIssues": 5
  },
  {
    "username": "kunalhemnani1",
    "totalPRs": 2,
    "mergedPRs": 2,
    "totalIssues": 0
  },
  {
    "username": "aamrindersingh",
    "totalPRs": 2,
    "mergedPRs": 2,
    "totalIssues": 0
  },
  {
    "username": "jams2",
    "totalPRs": 2,
    "mergedPRs": 2,
    "totalIssues": 0
  },
  {
    "username": "Adithya00012",
    "totalPRs": 9,
    "mergedPRs": 1,
    "totalIssues": 0
  },
  {
    "username": "indreshmishra566-stack",
    "totalPRs": 6,
    "mergedPRs": 1,
    "totalIssues": 0
  },
  {
    "username": "Copilot",
    "totalPRs": 5,
    "mergedPRs": 1,
    "totalIssues": 0
  },
  {
    "username": "Samya-Agg",
    "totalPRs": 5,
    "mergedPRs": 1,
    "totalIssues": 1
  },
  {
    "username": "SRINIVASBN",
    "totalPRs": 5,
    "mergedPRs": 1,
    "totalIssues": 0
  },
  {
    "username": "Kunal241207",
    "totalPRs": 5,
    "mergedPRs": 1,
    "totalIssues": 0
  },
  {
    "username": "Ritik-pixel28",
    "totalPRs": 5,
    "mergedPRs": 1,
    "totalIssues": 0
  },
  {
    "username": "rypptc",
    "totalPRs": 4,
    "mergedPRs": 1,
    "totalIssues": 6
  },
  {
    "username": "Dewolf1",
    "totalPRs": 4,
    "mergedPRs": 1,
    "totalIssues": 0
  },
  {
    "username": "paulschreiber",
    "totalPRs": 4,
    "mergedPRs": 1,
    "totalIssues": 0
  },
  {
    "username": "tomkins",
    "totalPRs": 3,
    "mergedPRs": 1,
    "totalIssues": 2
  },
  {
    "username": "emmanuelmingo",
    "totalPRs": 3,
    "mergedPRs": 1,
    "totalIssues": 1
  },
  {
    "username": "lasse-cs",
    "totalPRs": 3,
    "mergedPRs": 1,
    "totalIssues": 2
  },
  {
    "username": "SathvikaTalari",
    "totalPRs": 3,
    "mergedPRs": 1,
    "totalIssues": 1
  },
  {
    "username": "aniketgupta011",
    "totalPRs": 3,
    "mergedPRs": 1,
    "totalIssues": 0
  },
  {
    "username": "bhavesh-210",
    "totalPRs": 3,
    "mergedPRs": 1,
    "totalIssues": 0
  },
  {
    "username": "Pinakapaanip",
    "totalPRs": 3,
    "mergedPRs": 1,
    "totalIssues": 0
  },
  {
    "username": "gogo55w",
    "totalPRs": 3,
    "mergedPRs": 1,
    "totalIssues": 0
  },
  {
    "username": "Ash092016",
    "totalPRs": 3,
    "mergedPRs": 1,
    "totalIssues": 3
  },
  {
    "username": "rehanxt5",
    "totalPRs": 3,
    "mergedPRs": 1,
    "totalIssues": 0
  },
  {
    "username": "Aviek2004",
    "totalPRs": 2,
    "mergedPRs": 1,
    "totalIssues": 0
  },
  {
    "username": "wiki-virus",
    "totalPRs": 2,
    "mergedPRs": 1,
    "totalIssues": 0
  },
  {
    "username": "MrButtCode",
    "totalPRs": 2,
    "mergedPRs": 1,
    "totalIssues": 0
  },
  {
    "username": "mishraa-G",
    "totalPRs": 2,
    "mergedPRs": 1,
    "totalIssues": 1
  },
  {
    "username": "rajumanoj333",
    "totalPRs": 1,
    "mergedPRs": 1,
    "totalIssues": 0
  },
  {
    "username": "SahuShweta",
    "totalPRs": 1,
    "mergedPRs": 1,
    "totalIssues": 0
  },
  {
    "username": "kreeti22",
    "totalPRs": 1,
    "mergedPRs": 1,
    "totalIssues": 0
  },
  {
    "username": "Neha-Singh-j",
    "totalPRs": 1,
    "mergedPRs": 1,
    "totalIssues": 0
  },
  {
    "username": "jayanthwritescode",
    "totalPRs": 1,
    "mergedPRs": 1,
    "totalIssues": 0
  },
  {
    "username": "hanumanraj07",
    "totalPRs": 1,
    "mergedPRs": 1,
    "totalIssues": 0
  },
  {
    "username": "Rachit-Kakkad1",
    "totalPRs": 1,
    "mergedPRs": 1,
    "totalIssues": 0
  },
  {
    "username": "ryanbasic1",
    "totalPRs": 1,
    "mergedPRs": 1,
    "totalIssues": 0
  },
  {
    "username": "wisdomgu",
    "totalPRs": 1,
    "mergedPRs": 1,
    "totalIssues": 0
  },
  {
    "username": "Ashraf-AlRashidi",
    "totalPRs": 1,
    "mergedPRs": 1,
    "totalIssues": 0
  },
  {
    "username": "tkolpaczek",
    "totalPRs": 1,
    "mergedPRs": 1,
    "totalIssues": 0
  },
  {
    "username": "amarnath-cdr",
    "totalPRs": 1,
    "mergedPRs": 1,
    "totalIssues": 0
  },
  {
    "username": "lucks07",
    "totalPRs": 1,
    "mergedPRs": 1,
    "totalIssues": 0
  },
  {
    "username": "nxm-05",
    "totalPRs": 1,
    "mergedPRs": 1,
    "totalIssues": 0
  },
  {
    "username": "harshitagrawalprogo",
    "totalPRs": 1,
    "mergedPRs": 1,
    "totalIssues": 0
  },
  {
    "username": "iffatnigar",
    "totalPRs": 1,
    "mergedPRs": 1,
    "totalIssues": 0
  },
  {
    "username": "utsav-pal",
    "totalPRs": 1,
    "mergedPRs": 1,
    "totalIssues": 0
  },
  {
    "username": "shreyasbhaskar2001",
    "totalPRs": 1,
    "mergedPRs": 1,
    "totalIssues": 0
  },
  {
    "username": "SarthakAag",
    "totalPRs": 1,
    "mergedPRs": 1,
    "totalIssues": 0
  },
  {
    "username": "samkitjain2007",
    "totalPRs": 1,
    "mergedPRs": 1,
    "totalIssues": 0
  },
  {
    "username": "aaahanamehrotra",
    "totalPRs": 1,
    "mergedPRs": 1,
    "totalIssues": 0
  },
  {
    "username": "Alok-work23",
    "totalPRs": 1,
    "mergedPRs": 1,
    "totalIssues": 0
  },
  {
    "username": "Mohammad8329",
    "totalPRs": 1,
    "mergedPRs": 1,
    "totalIssues": 0
  },
  {
    "username": "akshatggupta",
    "totalPRs": 1,
    "mergedPRs": 1,
    "totalIssues": 0
  },
  {
    "username": "KhushiB03",
    "totalPRs": 1,
    "mergedPRs": 1,
    "totalIssues": 0
  },
  {
    "username": "NotTushar-dotcom",
    "totalPRs": 1,
    "mergedPRs": 1,
    "totalIssues": 0
  },
  {
    "username": "CodeVoyager3",
    "totalPRs": 1,
    "mergedPRs": 1,
    "totalIssues": 0
  },
  {
    "username": "blachcat",
    "totalPRs": 1,
    "mergedPRs": 1,
    "totalIssues": 0
  },
  {
    "username": "prince11111111111",
    "totalPRs": 1,
    "mergedPRs": 1,
    "totalIssues": 0
  },
  {
    "username": "SaptakS",
    "totalPRs": 1,
    "mergedPRs": 1,
    "totalIssues": 0
  },
  {
    "username": "bruecksen",
    "totalPRs": 1,
    "mergedPRs": 1,
    "totalIssues": 1
  },
  {
    "username": "Mr0grog",
    "totalPRs": 1,
    "mergedPRs": 1,
    "totalIssues": 2
  },
  {
    "username": "SAHIL15KP",
    "totalPRs": 1,
    "mergedPRs": 1,
    "totalIssues": 0
  },
  {
    "username": "darshankerkar",
    "totalPRs": 1,
    "mergedPRs": 1,
    "totalIssues": 0
  },
  {
    "username": "garrettc",
    "totalPRs": 1,
    "mergedPRs": 1,
    "totalIssues": 0
  },
  {
    "username": "namansharmapvt04-dot",
    "totalPRs": 1,
    "mergedPRs": 1,
    "totalIssues": 0
  },
  {
    "username": "cnk",
    "totalPRs": 1,
    "mergedPRs": 1,
    "totalIssues": 1
  },
  {
    "username": "mgax",
    "totalPRs": 1,
    "mergedPRs": 1,
    "totalIssues": 0
  },
  {
    "username": "yuvrajsingh0125",
    "totalPRs": 1,
    "mergedPRs": 1,
    "totalIssues": 0
  },
  {
    "username": "Saptami191",
    "totalPRs": 6,
    "mergedPRs": 0,
    "totalIssues": 0
  },
  {
    "username": "Saloni021-kashyap",
    "totalPRs": 5,
    "mergedPRs": 0,
    "totalIssues": 0
  },
  {
    "username": "Ronak-vegad",
    "totalPRs": 5,
    "mergedPRs": 0,
    "totalIssues": 0
  },
  {
    "username": "gaumrab",
    "totalPRs": 4,
    "mergedPRs": 0,
    "totalIssues": 0
  },
  {
    "username": "siddheshwar-9897",
    "totalPRs": 4,
    "mergedPRs": 0,
    "totalIssues": 0
  },
  {
    "username": "codxbrexx",
    "totalPRs": 4,
    "mergedPRs": 0,
    "totalIssues": 0
  },
  {
    "username": "pranitaurlam",
    "totalPRs": 4,
    "mergedPRs": 0,
    "totalIssues": 0
  },
  {
    "username": "Shubhamyadav93",
    "totalPRs": 4,
    "mergedPRs": 0,
    "totalIssues": 0
  },
  {
    "username": "pranavmanglik",
    "totalPRs": 3,
    "mergedPRs": 0,
    "totalIssues": 0
  },
  {
    "username": "artsbysree",
    "totalPRs": 3,
    "mergedPRs": 0,
    "totalIssues": 0
  },
  {
    "username": "Tuvshinbayar-hub",
    "totalPRs": 3,
    "mergedPRs": 0,
    "totalIssues": 0
  },
  {
    "username": "ZobiyaH",
    "totalPRs": 3,
    "mergedPRs": 0,
    "totalIssues": 0
  },
  {
    "username": "joeyjurjens",
    "totalPRs": 3,
    "mergedPRs": 0,
    "totalIssues": 2
  },
  {
    "username": "SuryaNarayanaa",
    "totalPRs": 3,
    "mergedPRs": 0,
    "totalIssues": 0
  },
  {
    "username": "adv0r",
    "totalPRs": 3,
    "mergedPRs": 0,
    "totalIssues": 0
  },
  {
    "username": "Semedw",
    "totalPRs": 3,
    "mergedPRs": 0,
    "totalIssues": 0
  },
  {
    "username": "pateldeep04",
    "totalPRs": 3,
    "mergedPRs": 0,
    "totalIssues": 0
  },
  {
    "username": "AYUSH676-JARVIS",
    "totalPRs": 3,
    "mergedPRs": 0,
    "totalIssues": 0
  },
  {
    "username": "manasvi-sahare",
    "totalPRs": 3,
    "mergedPRs": 0,
    "totalIssues": 0
  },
  {
    "username": "ShashanthSamala",
    "totalPRs": 3,
    "mergedPRs": 0,
    "totalIssues": 0
  },
  {
    "username": "ABHISHEKHOLAGUNDI",
    "totalPRs": 3,
    "mergedPRs": 0,
    "totalIssues": 0
  },
  {
    "username": "Aman-Cool",
    "totalPRs": 3,
    "mergedPRs": 0,
    "totalIssues": 0
  },
  {
    "username": "Soumya-codr",
    "totalPRs": 3,
    "mergedPRs": 0,
    "totalIssues": 0
  },
  {
    "username": "logicalavi09",
    "totalPRs": 3,
    "mergedPRs": 0,
    "totalIssues": 0
  },
  {
    "username": "pantha704",
    "totalPRs": 3,
    "mergedPRs": 0,
    "totalIssues": 0
  },
  {
    "username": "dchukhin",
    "totalPRs": 3,
    "mergedPRs": 0,
    "totalIssues": 1
  },
  {
    "username": "shalvirajpura2",
    "totalPRs": 2,
    "mergedPRs": 0,
    "totalIssues": 0
  },
  {
    "username": "Bhuvaneshwari-bhu",
    "totalPRs": 2,
    "mergedPRs": 0,
    "totalIssues": 0
  },
  {
    "username": "Quant-001",
    "totalPRs": 2,
    "mergedPRs": 0,
    "totalIssues": 0
  },
  {
    "username": "rajesh-puripanda",
    "totalPRs": 2,
    "mergedPRs": 0,
    "totalIssues": 0
  },
  {
    "username": "kritsii",
    "totalPRs": 2,
    "mergedPRs": 0,
    "totalIssues": 1
  },
  {
    "username": "Hamza2706",
    "totalPRs": 2,
    "mergedPRs": 0,
    "totalIssues": 0
  },
  {
    "username": "SebCorbin",
    "totalPRs": 2,
    "mergedPRs": 0,
    "totalIssues": 2
  },
  {
    "username": "varsh00l",
    "totalPRs": 2,
    "mergedPRs": 0,
    "totalIssues": 0
  },
  {
    "username": "hugnia",
    "totalPRs": 2,
    "mergedPRs": 0,
    "totalIssues": 0
  },
  {
    "username": "andreasnuesslein",
    "totalPRs": 2,
    "mergedPRs": 0,
    "totalIssues": 0
  },
  {
    "username": "Rudhrakshdeethi",
    "totalPRs": 2,
    "mergedPRs": 0,
    "totalIssues": 0
  },
  {
    "username": "abhishekshah5486",
    "totalPRs": 2,
    "mergedPRs": 0,
    "totalIssues": 0
  },
  {
    "username": "MaciekBaron",
    "totalPRs": 2,
    "mergedPRs": 0,
    "totalIssues": 3
  },
  {
    "username": "VMshall",
    "totalPRs": 2,
    "mergedPRs": 0,
    "totalIssues": 0
  },
  {
    "username": "alxbridge",
    "totalPRs": 2,
    "mergedPRs": 0,
    "totalIssues": 2
  },
  {
    "username": "Kgupta62",
    "totalPRs": 2,
    "mergedPRs": 0,
    "totalIssues": 0
  },
  {
    "username": "parthib0019",
    "totalPRs": 2,
    "mergedPRs": 0,
    "totalIssues": 0
  },
  {
    "username": "Pavan2coder",
    "totalPRs": 2,
    "mergedPRs": 0,
    "totalIssues": 0
  },
  {
    "username": "fabienheureux",
    "totalPRs": 2,
    "mergedPRs": 0,
    "totalIssues": 0
  },
  {
    "username": "Srvankit",
    "totalPRs": 2,
    "mergedPRs": 0,
    "totalIssues": 0
  },
  {
    "username": "jawad-khan",
    "totalPRs": 2,
    "mergedPRs": 0,
    "totalIssues": 0
  },
  {
    "username": "blfpd",
    "totalPRs": 2,
    "mergedPRs": 0,
    "totalIssues": 0
  },
  {
    "username": "tanmay0996",
    "totalPRs": 2,
    "mergedPRs": 0,
    "totalIssues": 0
  },
  {
    "username": "santhil-cyber",
    "totalPRs": 2,
    "mergedPRs": 0,
    "totalIssues": 0
  },
  {
    "username": "agsaru",
    "totalPRs": 2,
    "mergedPRs": 0,
    "totalIssues": 0
  },
  {
    "username": "Sukuna0007Abhi",
    "totalPRs": 2,
    "mergedPRs": 0,
    "totalIssues": 0
  },
  {
    "username": "ihor-voronin",
    "totalPRs": 2,
    "mergedPRs": 0,
    "totalIssues": 2
  },
  {
    "username": "rob-browncc",
    "totalPRs": 1,
    "mergedPRs": 0,
    "totalIssues": 0
  },
  {
    "username": "SAY-5",
    "totalPRs": 1,
    "mergedPRs": 0,
    "totalIssues": 0
  },
  {
    "username": "tejash-sr",
    "totalPRs": 1,
    "mergedPRs": 0,
    "totalIssues": 1
  },
  {
    "username": "itwaasyou",
    "totalPRs": 1,
    "mergedPRs": 0,
    "totalIssues": 0
  },
  {
    "username": "suyash469",
    "totalPRs": 1,
    "mergedPRs": 0,
    "totalIssues": 1
  },
  {
    "username": "bitbytecyber",
    "totalPRs": 1,
    "mergedPRs": 0,
    "totalIssues": 0
  },
  {
    "username": "Anushreebasics",
    "totalPRs": 1,
    "mergedPRs": 0,
    "totalIssues": 0
  },
  {
    "username": "bhageshsharma777",
    "totalPRs": 1,
    "mergedPRs": 0,
    "totalIssues": 0
  },
  {
    "username": "botbikamordehai2-sketch",
    "totalPRs": 1,
    "mergedPRs": 0,
    "totalIssues": 0
  },
  {
    "username": "ayushk687",
    "totalPRs": 1,
    "mergedPRs": 0,
    "totalIssues": 0
  },
  {
    "username": "JiwaniZakir",
    "totalPRs": 1,
    "mergedPRs": 0,
    "totalIssues": 0
  },
  {
    "username": "anzzyspeaksgit",
    "totalPRs": 1,
    "mergedPRs": 0,
    "totalIssues": 0
  },
  {
    "username": "mahmoudnasser1561",
    "totalPRs": 1,
    "mergedPRs": 0,
    "totalIssues": 0
  },
  {
    "username": "hacker4257",
    "totalPRs": 1,
    "mergedPRs": 0,
    "totalIssues": 0
  },
  {
    "username": "matisgagneux21",
    "totalPRs": 1,
    "mergedPRs": 0,
    "totalIssues": 0
  },
  {
    "username": "utafrali",
    "totalPRs": 1,
    "mergedPRs": 0,
    "totalIssues": 0
  },
  {
    "username": "RheagalFire",
    "totalPRs": 1,
    "mergedPRs": 0,
    "totalIssues": 0
  },
  {
    "username": "JNaftali",
    "totalPRs": 1,
    "mergedPRs": 0,
    "totalIssues": 2
  },
  {
    "username": "Iser12",
    "totalPRs": 1,
    "mergedPRs": 0,
    "totalIssues": 0
  },
  {
    "username": "jamesbiggs",
    "totalPRs": 1,
    "mergedPRs": 0,
    "totalIssues": 2
  },
  {
    "username": "tyndyll",
    "totalPRs": 1,
    "mergedPRs": 0,
    "totalIssues": 0
  },
  {
    "username": "vedanth5",
    "totalPRs": 1,
    "mergedPRs": 0,
    "totalIssues": 0
  },
  {
    "username": "S3DFX-CYBER",
    "totalPRs": 1,
    "mergedPRs": 0,
    "totalIssues": 0
  },
  {
    "username": "kevinhowbrook",
    "totalPRs": 1,
    "mergedPRs": 0,
    "totalIssues": 1
  },
  {
    "username": "armorbreak001",
    "totalPRs": 1,
    "mergedPRs": 0,
    "totalIssues": 0
  },
  {
    "username": "rowanhagey",
    "totalPRs": 1,
    "mergedPRs": 0,
    "totalIssues": 0
  },
  {
    "username": "Beeram12",
    "totalPRs": 1,
    "mergedPRs": 0,
    "totalIssues": 0
  },
  {
    "username": "charliewolf",
    "totalPRs": 1,
    "mergedPRs": 0,
    "totalIssues": 0
  },
  {
    "username": "hxrshxz",
    "totalPRs": 1,
    "mergedPRs": 0,
    "totalIssues": 0
  },
  {
    "username": "ehinuel",
    "totalPRs": 1,
    "mergedPRs": 0,
    "totalIssues": 0
  },
  {
    "username": "octomaanav",
    "totalPRs": 1,
    "mergedPRs": 0,
    "totalIssues": 0
  },
  {
    "username": "ianmeigh",
    "totalPRs": 1,
    "mergedPRs": 0,
    "totalIssues": 1
  },
  {
    "username": "divu050704",
    "totalPRs": 1,
    "mergedPRs": 0,
    "totalIssues": 0
  },
  {
    "username": "Abhi090907",
    "totalPRs": 1,
    "mergedPRs": 0,
    "totalIssues": 0
  },
  {
    "username": "MrCoderShaurya",
    "totalPRs": 1,
    "mergedPRs": 0,
    "totalIssues": 0
  },
  {
    "username": "muskanmaurya",
    "totalPRs": 1,
    "mergedPRs": 0,
    "totalIssues": 0
  },
  {
    "username": "tomusher",
    "totalPRs": 1,
    "mergedPRs": 0,
    "totalIssues": 0
  },
  {
    "username": "vishal-tiwari9",
    "totalPRs": 1,
    "mergedPRs": 0,
    "totalIssues": 0
  },
  {
    "username": "muzman123",
    "totalPRs": 1,
    "mergedPRs": 0,
    "totalIssues": 0
  },
  {
    "username": "Abmarne",
    "totalPRs": 1,
    "mergedPRs": 0,
    "totalIssues": 0
  },
  {
    "username": "Ewan-Dkhar",
    "totalPRs": 1,
    "mergedPRs": 0,
    "totalIssues": 0
  },
  {
    "username": "OmH3",
    "totalPRs": 1,
    "mergedPRs": 0,
    "totalIssues": 0
  },
  {
    "username": "Purushothamreddy23",
    "totalPRs": 1,
    "mergedPRs": 0,
    "totalIssues": 0
  },
  {
    "username": "axoplasm",
    "totalPRs": 1,
    "mergedPRs": 0,
    "totalIssues": 2
  },
  {
    "username": "jmwhitworth",
    "totalPRs": 1,
    "mergedPRs": 0,
    "totalIssues": 0
  },
  {
    "username": "maycuatroi1",
    "totalPRs": 1,
    "mergedPRs": 0,
    "totalIssues": 0
  },
  {
    "username": "Rampujitha-123",
    "totalPRs": 1,
    "mergedPRs": 0,
    "totalIssues": 1
  },
  {
    "username": "enadeau",
    "totalPRs": 1,
    "mergedPRs": 0,
    "totalIssues": 1
  },
  {
    "username": "non4me21",
    "totalPRs": 1,
    "mergedPRs": 0,
    "totalIssues": 1
  },
  {
    "username": "sanyamkansal",
    "totalPRs": 1,
    "mergedPRs": 0,
    "totalIssues": 0
  },
  {
    "username": "praveen-86176",
    "totalPRs": 1,
    "mergedPRs": 0,
    "totalIssues": 0
  },
  {
    "username": "sapnasen21",
    "totalPRs": 1,
    "mergedPRs": 0,
    "totalIssues": 0
  },
  {
    "username": "arushii09",
    "totalPRs": 1,
    "mergedPRs": 0,
    "totalIssues": 0
  },
  {
    "username": "solarissmoke",
    "totalPRs": 1,
    "mergedPRs": 0,
    "totalIssues": 0
  },
  {
    "username": "mannatjain11465-netizen",
    "totalPRs": 1,
    "mergedPRs": 0,
    "totalIssues": 0
  },
  {
    "username": "kaedroho",
    "totalPRs": 1,
    "mergedPRs": 0,
    "totalIssues": 0
  },
  {
    "username": "AlexMKX",
    "totalPRs": 1,
    "mergedPRs": 0,
    "totalIssues": 0
  },
  {
    "username": "shloksharmawork",
    "totalPRs": 1,
    "mergedPRs": 0,
    "totalIssues": 0
  },
  {
    "username": "Yug210705",
    "totalPRs": 1,
    "mergedPRs": 0,
    "totalIssues": 1
  },
  {
    "username": "pashaarshad",
    "totalPRs": 1,
    "mergedPRs": 0,
    "totalIssues": 0
  },
  {
    "username": "NotIbutme",
    "totalPRs": 1,
    "mergedPRs": 0,
    "totalIssues": 0
  },
  {
    "username": "AshuShekhar07",
    "totalPRs": 1,
    "mergedPRs": 0,
    "totalIssues": 0
  },
  {
    "username": "parthbeingparth",
    "totalPRs": 1,
    "mergedPRs": 0,
    "totalIssues": 0
  },
  {
    "username": "SerkanKorkusuz",
    "totalPRs": 1,
    "mergedPRs": 0,
    "totalIssues": 1
  },
  {
    "username": "amit-kumbhare",
    "totalPRs": 1,
    "mergedPRs": 0,
    "totalIssues": 0
  },
  {
    "username": "Mohima6",
    "totalPRs": 1,
    "mergedPRs": 0,
    "totalIssues": 0
  },
  {
    "username": "codeforge19",
    "totalPRs": 1,
    "mergedPRs": 0,
    "totalIssues": 0
  },
  {
    "username": "ElavarasiArumugam",
    "totalPRs": 1,
    "mergedPRs": 0,
    "totalIssues": 0
  },
  {
    "username": "AnvayKharb",
    "totalPRs": 1,
    "mergedPRs": 0,
    "totalIssues": 1
  },
  {
    "username": "31puneet",
    "totalPRs": 1,
    "mergedPRs": 0,
    "totalIssues": 0
  },
  {
    "username": "vikash7485",
    "totalPRs": 1,
    "mergedPRs": 0,
    "totalIssues": 0
  },
  {
    "username": "piyushpanchal114",
    "totalPRs": 1,
    "mergedPRs": 0,
    "totalIssues": 0
  },
  {
    "username": "sharma-anushka",
    "totalPRs": 1,
    "mergedPRs": 0,
    "totalIssues": 0
  },
  {
    "username": "valkrypton",
    "totalPRs": 1,
    "mergedPRs": 0,
    "totalIssues": 0
  },
  {
    "username": "nim65s",
    "totalPRs": 1,
    "mergedPRs": 0,
    "totalIssues": 0
  },
  {
    "username": "krrish175-byte",
    "totalPRs": 1,
    "mergedPRs": 0,
    "totalIssues": 0
  },
  {
    "username": "Yashagarwal9798",
    "totalPRs": 1,
    "mergedPRs": 0,
    "totalIssues": 0
  },
  {
    "username": "ATOMworkplace",
    "totalPRs": 1,
    "mergedPRs": 0,
    "totalIssues": 0
  },
  {
    "username": "kehach07",
    "totalPRs": 1,
    "mergedPRs": 0,
    "totalIssues": 1
  },
  {
    "username": "JAYANTJOSHI001",
    "totalPRs": 1,
    "mergedPRs": 0,
    "totalIssues": 0
  },
  {
    "username": "dkirkham",
    "totalPRs": 1,
    "mergedPRs": 0,
    "totalIssues": 0
  },
  {
    "username": "socketz",
    "totalPRs": 1,
    "mergedPRs": 0,
    "totalIssues": 0
  },
  {
    "username": "efrysf",
    "totalPRs": 1,
    "mergedPRs": 0,
    "totalIssues": 0
  },
  {
    "username": "Sarthak160",
    "totalPRs": 1,
    "mergedPRs": 0,
    "totalIssues": 0
  },
  {
    "username": "Azadron228",
    "totalPRs": 1,
    "mergedPRs": 0,
    "totalIssues": 0
  },
  {
    "username": "pre-commit-ci[bot]",
    "totalPRs": 1,
    "mergedPRs": 0,
    "totalIssues": 0
  },
  {
    "username": "jtdevos",
    "totalPRs": 1,
    "mergedPRs": 0,
    "totalIssues": 0
  },
  {
    "username": "dimalavrishin",
    "totalPRs": 1,
    "mergedPRs": 0,
    "totalIssues": 1
  },
  {
    "username": "AzharAliCodes",
    "totalPRs": 0,
    "mergedPRs": 0,
    "totalIssues": 1
  },
  {
    "username": "neilbulloch",
    "totalPRs": 0,
    "mergedPRs": 0,
    "totalIssues": 1
  },
  {
    "username": "erkandem",
    "totalPRs": 0,
    "mergedPRs": 0,
    "totalIssues": 1
  },
  {
    "username": "ababic",
    "totalPRs": 0,
    "mergedPRs": 0,
    "totalIssues": 1
  },
  {
    "username": "preet-kour",
    "totalPRs": 0,
    "mergedPRs": 0,
    "totalIssues": 1
  },
  {
    "username": "anuradha1304",
    "totalPRs": 0,
    "mergedPRs": 0,
    "totalIssues": 1
  },
  {
    "username": "harikadanduprolu",
    "totalPRs": 0,
    "mergedPRs": 0,
    "totalIssues": 1
  },
  {
    "username": "vikram-2101",
    "totalPRs": 0,
    "mergedPRs": 0,
    "totalIssues": 5
  },
  {
    "username": "GhanshyamJha05",
    "totalPRs": 0,
    "mergedPRs": 0,
    "totalIssues": 2
  },
  {
    "username": "minusf",
    "totalPRs": 0,
    "mergedPRs": 0,
    "totalIssues": 2
  },
  {
    "username": "PathakAman66",
    "totalPRs": 0,
    "mergedPRs": 0,
    "totalIssues": 6
  },
  {
    "username": "tomdyson",
    "totalPRs": 0,
    "mergedPRs": 0,
    "totalIssues": 1
  },
  {
    "username": "Scotchester",
    "totalPRs": 0,
    "mergedPRs": 0,
    "totalIssues": 3
  },
  {
    "username": "Lalit7374",
    "totalPRs": 0,
    "mergedPRs": 0,
    "totalIssues": 1
  },
  {
    "username": "anthonybaxter",
    "totalPRs": 0,
    "mergedPRs": 0,
    "totalIssues": 1
  },
  {
    "username": "enzedonline",
    "totalPRs": 0,
    "mergedPRs": 0,
    "totalIssues": 2
  },
  {
    "username": "bjorn-fabrique",
    "totalPRs": 0,
    "mergedPRs": 0,
    "totalIssues": 1
  },
  {
    "username": "nickAalst",
    "totalPRs": 0,
    "mergedPRs": 0,
    "totalIssues": 1
  },
  {
    "username": "jpdevdotcom",
    "totalPRs": 0,
    "mergedPRs": 0,
    "totalIssues": 1
  },
  {
    "username": "UDAR-TomH",
    "totalPRs": 0,
    "mergedPRs": 0,
    "totalIssues": 2
  },
  {
    "username": "Morefra",
    "totalPRs": 0,
    "mergedPRs": 0,
    "totalIssues": 1
  },
  {
    "username": "Yemeni",
    "totalPRs": 0,
    "mergedPRs": 0,
    "totalIssues": 1
  },
  {
    "username": "Nigel2392",
    "totalPRs": 0,
    "mergedPRs": 0,
    "totalIssues": 3
  },
  {
    "username": "anselmbradford",
    "totalPRs": 0,
    "mergedPRs": 0,
    "totalIssues": 1
  },
  {
    "username": "danmanix",
    "totalPRs": 0,
    "mergedPRs": 0,
    "totalIssues": 3
  },
  {
    "username": "coredumperror",
    "totalPRs": 0,
    "mergedPRs": 0,
    "totalIssues": 1
  },
  {
    "username": "sheepman4267",
    "totalPRs": 0,
    "mergedPRs": 0,
    "totalIssues": 1
  },
  {
    "username": "weber-s",
    "totalPRs": 0,
    "mergedPRs": 0,
    "totalIssues": 2
  },
  {
    "username": "kunambi",
    "totalPRs": 0,
    "mergedPRs": 0,
    "totalIssues": 1
  },
  {
    "username": "ahosgood",
    "totalPRs": 0,
    "mergedPRs": 0,
    "totalIssues": 1
  },
  {
    "username": "allcaps",
    "totalPRs": 0,
    "mergedPRs": 0,
    "totalIssues": 1
  },
  {
    "username": "nimasmi",
    "totalPRs": 0,
    "mergedPRs": 0,
    "totalIssues": 1
  },
  {
    "username": "fabianhohly",
    "totalPRs": 0,
    "mergedPRs": 0,
    "totalIssues": 1
  },
  {
    "username": "frague59",
    "totalPRs": 0,
    "mergedPRs": 0,
    "totalIssues": 1
  },
  {
    "username": "sanjeevz3009",
    "totalPRs": 0,
    "mergedPRs": 0,
    "totalIssues": 1
  },
  {
    "username": "Ash-Crow",
    "totalPRs": 0,
    "mergedPRs": 0,
    "totalIssues": 1
  },
  {
    "username": "shravankumar8",
    "totalPRs": 0,
    "mergedPRs": 0,
    "totalIssues": 1
  },
  {
    "username": "jeverling",
    "totalPRs": 0,
    "mergedPRs": 0,
    "totalIssues": 1
  },
  {
    "username": "poswald",
    "totalPRs": 0,
    "mergedPRs": 0,
    "totalIssues": 1
  },
  {
    "username": "onno-timmerman",
    "totalPRs": 0,
    "mergedPRs": 0,
    "totalIssues": 3
  },
  {
    "username": "tim-mccurrach",
    "totalPRs": 0,
    "mergedPRs": 0,
    "totalIssues": 1
  },
  {
    "username": "PanosDine",
    "totalPRs": 0,
    "mergedPRs": 0,
    "totalIssues": 1
  },
  {
    "username": "mojeto",
    "totalPRs": 0,
    "mergedPRs": 0,
    "totalIssues": 1
  },
  {
    "username": "SalahAdDin",
    "totalPRs": 0,
    "mergedPRs": 0,
    "totalIssues": 1
  },
  {
    "username": "joaoccf56",
    "totalPRs": 0,
    "mergedPRs": 0,
    "totalIssues": 1
  },
  {
    "username": "youzarsiph",
    "totalPRs": 0,
    "mergedPRs": 0,
    "totalIssues": 1
  },
  {
    "username": "garyayo",
    "totalPRs": 0,
    "mergedPRs": 0,
    "totalIssues": 1
  },
  {
    "username": "alex-akqa-leap",
    "totalPRs": 0,
    "mergedPRs": 0,
    "totalIssues": 1
  },
  {
    "username": "seb-b",
    "totalPRs": 0,
    "mergedPRs": 0,
    "totalIssues": 1
  },
  {
    "username": "sowinski",
    "totalPRs": 0,
    "mergedPRs": 0,
    "totalIssues": 1
  },
  {
    "username": "Luzzzi",
    "totalPRs": 0,
    "mergedPRs": 0,
    "totalIssues": 1
  },
  {
    "username": "MarcoSteinacher",
    "totalPRs": 0,
    "mergedPRs": 0,
    "totalIssues": 1
  },
  {
    "username": "benebun",
    "totalPRs": 0,
    "mergedPRs": 0,
    "totalIssues": 1
  },
  {
    "username": "byte-for-byte",
    "totalPRs": 0,
    "mergedPRs": 0,
    "totalIssues": 1
  },
  {
    "username": "andre-fuchs",
    "totalPRs": 0,
    "mergedPRs": 0,
    "totalIssues": 2
  },
  {
    "username": "MebinAbraham",
    "totalPRs": 0,
    "mergedPRs": 0,
    "totalIssues": 1
  },
  {
    "username": "annapelliccitbx",
    "totalPRs": 0,
    "mergedPRs": 0,
    "totalIssues": 1
  },
  {
    "username": "bva-chun",
    "totalPRs": 0,
    "mergedPRs": 0,
    "totalIssues": 1
  },
  {
    "username": "giftig",
    "totalPRs": 0,
    "mergedPRs": 0,
    "totalIssues": 1
  },
  {
    "username": "rachelhsmith",
    "totalPRs": 0,
    "mergedPRs": 0,
    "totalIssues": 1
  },
  {
    "username": "shaswatHota",
    "totalPRs": 0,
    "mergedPRs": 0,
    "totalIssues": 1
  },
  {
    "username": "leonli8012",
    "totalPRs": 0,
    "mergedPRs": 0,
    "totalIssues": 1
  },
  {
    "username": "PRITAM-TU",
    "totalPRs": 0,
    "mergedPRs": 0,
    "totalIssues": 2
  },
  {
    "username": "Bhupendra-glitch",
    "totalPRs": 0,
    "mergedPRs": 0,
    "totalIssues": 1
  },
  {
    "username": "sephii",
    "totalPRs": 0,
    "mergedPRs": 0,
    "totalIssues": 1
  },
  {
    "username": "krzysztofjeziorny",
    "totalPRs": 0,
    "mergedPRs": 0,
    "totalIssues": 1
  },
  {
    "username": "remles1",
    "totalPRs": 0,
    "mergedPRs": 0,
    "totalIssues": 1
  },
  {
    "username": "gr8jam",
    "totalPRs": 0,
    "mergedPRs": 0,
    "totalIssues": 1
  },
  {
    "username": "maribedran",
    "totalPRs": 0,
    "mergedPRs": 0,
    "totalIssues": 1
  }
]